<items>
<item>
    <title>Animais Fantásticos e Onde Habitam (2016)</title>
    <link>plugin://plugin.video.elementum/play?uri=magnet:?xt=urn:btih:a438fdf841db95185b638ed2f9fe94ef0a5c826b</link>
    <thumbnail>https://www.themoviedb.org/t/p/w600_and_h900_bestv2/sGkt9ekX5cgRYKRIiJM27Xp3piR.jpg</thumbnail>
    <duration>7920</duration>
    <genre>Fantasia, Aventura, Ação</genre>
    <meta>
        <content>movie</content>
        <imdb>tt3183660</imdb>
        <year>2016</year>
        <genre>Fantasia, Aventura, Ação</genre>
    </meta>
</item>
<item>
    <title>Animais Fantásticos: Os Crimes de Grindelwald (2018)</title>
    <link>plugin://plugin.video.elementum/play?uri=magnet:?xt=urn:btih:d2bee4130e8aeff24514b44698ab499c374f7559</link>
    <thumbnail>https://www.themoviedb.org/t/p/w600_and_h900_bestv2/oANEhQDQ3eB8tcqRPSzABim8oNg.jpg</thumbnail>
    <duration>7980</duration>
    <genre>Fantasia, Aventura, Ação</genre>
    <meta>
        <content>movie</content>
        <imdb>tt4123430</imdb>
        <year>2018</year>
        <genre>Fantasia, Aventura, Ação</genre>
    </meta>
</item>
<item>
    <title>Animais Fantásticos: Os Segredos de Dumbledore (2022)</title>
    <link>plugin://plugin.video.elementum/play?uri=magnet:?xt=urn:btih:9d6444fd3ac94d6b3f3ad8a083968dee638340fd</link>
    <thumbnail>https://www.themoviedb.org/t/p/w600_and_h900_bestv2/gopGghuMtmdMviBcl9G0JfVB2RZ.jpg</thumbnail>
    <duration>8520</duration>
    <genre>Fantasia, Aventura, Ação</genre>
    <meta>
        <content>movie</content>
        <imdb>tt4123432</imdb>
        <year>2022</year>
        <genre>Fantasia, Aventura, Ação</genre>
    </meta>
</item>
</items>
