
<items>
<item>
			<title>O Poderoso Chefão (1972)</title>
			<link>plugin://plugin.video.elementum/play?uri=magnet:?xt=urn:btih:c34911e5ca4518978719cfef123e204ec7905edd</link>
			<thumbnail>https://image.tmdb.org/t/p/w342/oS3mn55v5jEBduZQp2ttzqxxbLQ.jpg</thumbnail>
			<genre>Drama, Thriller, Crime</genre>
  <meta>
<imdb_id>TT0068646</imdb_id>
<year>1972</year>
</meta>
		</item>
		<item>
			<title>O Poderoso Chefão II (1974)</title>
			<link>plugin://plugin.video.elementum/play?uri=magnet:?xt=urn:btih:a0fad811eff971b3bc2fff1219e1052ee2b3c6ec</link>
			<thumbnail>https://image.tmdb.org/t/p/w342/yB3AkkGMFplGlnPqQZ38W7bdD10.jpg</thumbnail>
			<genre>Drama, Thriller, Crime</genre>
           <meta>
<imdb_id>TT0071562</imdb_id>
<year>1974</year>
</meta>
		</item>
		<item>
			<title>O Poderoso Chefão III (1990)</title>
			<link>plugin://plugin.video.elementum/play?uri=magnet:?xt=urn:btih:83b9837b116727ff698d2743c0b4a869a2e1c281</link>
			<thumbnail>https://image.tmdb.org/t/p/w342/6kKs45futNbmKkt4SxousPqHDKP.jpg</thumbnail>
			<genre>Drama, Thriller, Crime</genre>
      <meta>
<imdb_id>TT0099647</imdb_id>
<year>1990</year>
</meta>
		</item>
	</items>
